LICENSE
NOTICE
xdyna/__init__.py
xdyna/da.py
xdyna/da_meta.py
xdyna/geometry.py
xdyna/ml.py
xdyna/protectfile.py
xdyna/sixtrack_jobs.py
xdyna-0.1.1.dist-info/LICENSE
xdyna-0.1.1.dist-info/WHEEL
xdyna-0.1.1.dist-info/METADATA
xdyna-0.1.1.dist-info/RECORD
