Metadata-Version: 2.1
Name: xdyna
Version: 0.1.1
Summary: Xsuite dynamics package
Home-page: https://github.com/xsuite/xdyna
License: Apache 2.0
Author: Frederik F. Van der Veken
Author-email: frederik@cern.ch
Requires-Python: >=3.8
Classifier: License :: Other/Proprietary License
Classifier: Programming Language :: Python :: 3
Classifier: Programming Language :: Python :: 3.8
Classifier: Programming Language :: Python :: 3.9
Classifier: Programming Language :: Python :: 3.10
Classifier: Programming Language :: Python :: 3.11
Requires-Dist: pandas (>=1.5.1)
Requires-Dist: scipy (>=1.9.3)
Project-URL: Repository, https://github.com/xsuite/xdyna
